zb_common/__init__.py
zb_common/common.py
zb_common-0.1.3.dist-info/DESCRIPTION.rst
zb_common-0.1.3.dist-info/METADATA
zb_common-0.1.3.dist-info/RECORD
zb_common-0.1.3.dist-info/WHEEL
zb_common-0.1.3.dist-info/metadata.json
zb_common-0.1.3.dist-info/top_level.txt
