Metadata-Version: 2.0
Name: zb-common
Version: 0.1.3
Summary: A package containing all the common utilities for the Zerobugz project
Home-page: http://pypi.python.org/pypi/zb-common/
Author: Manjunath Somashekar
Author-email: ujnamss@gmail.com
License: UNKNOWN
Keywords: synthetic,data,generation
Platform: UNKNOWN
Classifier: Programming Language :: Python
Classifier: Programming Language :: Python :: 2.7
Classifier: Programming Language :: Python :: 3
Classifier: Development Status :: 2 - Pre-Alpha
Classifier: Environment :: Other Environment
Classifier: Intended Audience :: Developers
Classifier: License :: OSI Approved :: GNU Library or Lesser General Public License (LGPL)
Classifier: Operating System :: OS Independent
Classifier: Topic :: Software Development :: Libraries :: Python Modules
Requires-Dist: configparser
Requires-Dist: future (>=0.16.0)
Requires-Dist: requests
Requires-Dist: slackclient (==1.3.1)
